langchain_openai_api_bridge/__init__.py
langchain_openai_api_bridge/assistant/__init__.py
langchain_openai_api_bridge/assistant/adapter/container.py
langchain_openai_api_bridge/assistant/adapter/langchain_input_content_adapter.py
langchain_openai_api_bridge/assistant/adapter/langgraph_event_to_openai_assistant_event_stream.py
langchain_openai_api_bridge/assistant/adapter/on_chat_model_end_handler.py
langchain_openai_api_bridge/assistant/adapter/on_chat_model_stream_handler.py
langchain_openai_api_bridge/assistant/adapter/on_tool_end_handler.py
langchain_openai_api_bridge/assistant/adapter/on_tool_start_handler.py
langchain_openai_api_bridge/assistant/adapter/openai_event_factory.py
langchain_openai_api_bridge/assistant/adapter/openai_message_content_adapter.py
langchain_openai_api_bridge/assistant/adapter/openai_message_factory.py
langchain_openai_api_bridge/assistant/adapter/thread_run_event_handler.py
langchain_openai_api_bridge/assistant/adapter/thread_to_langchain_input_messages_service.py
langchain_openai_api_bridge/assistant/assistant_message_service.py
langchain_openai_api_bridge/assistant/assistant_run_service.py
langchain_openai_api_bridge/assistant/assistant_stream_event_adapter.py
langchain_openai_api_bridge/assistant/assistant_thread_service.py
langchain_openai_api_bridge/assistant/create_thread_api_dto.py
langchain_openai_api_bridge/assistant/create_thread_message_api_dto.py
langchain_openai_api_bridge/assistant/create_thread_runs_api_dto.py
langchain_openai_api_bridge/assistant/openai_run_factory.py
langchain_openai_api_bridge/assistant/repository/__init__.py
langchain_openai_api_bridge/assistant/repository/in_memory_message_repository.py
langchain_openai_api_bridge/assistant/repository/in_memory_run_repository.py
langchain_openai_api_bridge/assistant/repository/in_memory_thread_repository.py
langchain_openai_api_bridge/assistant/repository/message_repository.py
langchain_openai_api_bridge/assistant/repository/run_repository.py
langchain_openai_api_bridge-1.0.0.dist-info/LICENSE
langchain_openai_api_bridge-1.0.0.dist-info/METADATA
langchain_openai_api_bridge-1.0.0.dist-info/WHEEL
langchain_openai_api_bridge-1.0.0.dist-info/entry_points.txt
langchain_openai_api_bridge-1.0.0.dist-info/RECORD
